README.rst
setup.py
Flask_CI.egg-info/PKG-INFO
Flask_CI.egg-info/SOURCES.txt
Flask_CI.egg-info/dependency_links.txt
Flask_CI.egg-info/not-zip-safe
Flask_CI.egg-info/requires.txt
Flask_CI.egg-info/top_level.txt
flask_ci/__init__.py
flask_ci/ci.py
flask_ci/tasks/__init__.py
flask_ci/tasks/pylint.rc
flask_ci/tasks/run_nose.py
flask_ci/tasks/run_pep8.py
flask_ci/tasks/run_pylint.py
flask_ci/util/__init__.py
flask_ci/util/constants.py