Metadata-Version: 1.1
Name: Flask-CI
Version: 1.1.24
Summary: Continuous Integration support for Flask
Home-page: https://github.com/vicenteneto/flask-ci
Author: Vicente Neto
Author-email: sneto.vicente@gmail.com
License: MIT
Keywords: ci,jenkins,hudson,flask,pylint,pep8,coverage,nose
Platform: UNKNOWN
Classifier: Development Status :: 4 - Beta
Classifier: Environment :: Web Environment
Classifier: Framework :: Flask
Classifier: Intended Audience :: Developers
Classifier: License :: OSI Approved :: MIT License
Classifier: Operating System :: OS Independent
Classifier: Programming Language :: Python
Classifier: Topic :: Internet :: WWW/HTTP :: Dynamic Content
Classifier: Topic :: Software Development :: Libraries :: Python Modules
Classifier: Topic :: Software Development :: Testing
